fJson/__init__.py
fJson/fjson.py
simple_fjson-0.1.4.post2.dist-info/LICENSE
simple_fjson-0.1.4.post2.dist-info/METADATA
simple_fjson-0.1.4.post2.dist-info/WHEEL
simple_fjson-0.1.4.post2.dist-info/top_level.txt
simple_fjson-0.1.4.post2.dist-info/RECORD
