Metadata-Version: 2.2
Name: simple-fjson
Version: 0.1.4.post2
Summary: A flexible JSON parser
Home-page: https://github.com/sjrsjz/fjson
Author: sjrsjz
Author-email: sjrsjz@gmail.com
Classifier: Programming Language :: Python :: 3
Classifier: License :: OSI Approved :: MIT License
Classifier: Operating System :: OS Independent
Requires-Python: >=3.6
License-File: LICENSE
Dynamic: author
Dynamic: author-email
Dynamic: classifier
Dynamic: description
Dynamic: description-content-type
Dynamic: home-page
Dynamic: requires-python
Dynamic: summary
